{
    "appname": "web_channel_spring",
    "namespace": "shank",
    "alias": "spring",
    "debug": false,
    "port": 3000,
    "outputStd": false,
    "viewsdir": "dist",
    "apiPrefix": "",
    "cacheURL": true,
    "statistics": true,
    "statisticsJaeger": true,
    "statisticsProm": true,
    "JaegerDebug": false,
    "JaegerSamplerType": "probabilistic",
    "JaegerSamplerParam": 0.1,
    "logs": {
        "level": "info"
    },
    "redisHosts": [
        { "host": "shank-redis-ha-master-svc.test-k8s-loda.svc.cluster.local", "port": 6379 }
    ],
    "blacklist": ["/controllers/black/black.js"],
    "cdnCacheTime": 120
}
